[
    {
        "title": "人們可能會這樣描述你",
        "options": [
            {
                "label": "果斷的、自信的、強勢的、目標導向的、決斷的、堅定的、主導的、競爭性的",
                "value": "d"
            },
            {
                "label": "有魅力的、外向的、熱情的、友善的、樂觀的、鼓舞人心的、健談的、充滿活力的",
                "value": "i"
            },
            {
                "label": "可靠的、友善的、耐心的、合作的、支持的、穩重的、忠誠的、和藹的",
                "value": "s"
            },
            {
                "label": "細心的、謹慎的、精確的、分析性的、有條理的、負責任的、徹底的、完美主義的",
                "value": "c"
            }
        ]
    },
    {
        "title": "最讓你感到挫折的是哪些人",
        "options": [
            {
                "label": "猶豫不決的人、缺乏行動力的人、過於小心翼翼的人",
                "value": "d"
            },
            {
                "label": "冷漠或缺乏熱情的人、過於嚴肅或不喜歡社交的人",
                "value": "i"
            },
            {
                "label": "喜歡變化和挑戰現狀的人、過於急躁或咄咄逼人的人",
                "value": "s"
            },
            {
                "label": "缺乏組織和計劃的人、不重視細節的人、隨意或草率行事的人",
                "value": "c"
            }
        ]
    },
    {
        "title": "開始一項專案時，你喜歡",
        "options": [
            {
                "label": "快速行動，設定明確的目標和期限，立即分配任務",
                "value": "d"
            },
            {
                "label": "鼓勵團隊，激發熱情，強調團隊合作",
                "value": "i"
            },
            {
                "label": "建立清晰的流程和步驟，確保每個人都理解並接受計劃",
                "value": "s"
            },
            {
                "label": "進行深入研究，確保計劃的每個細節都經過充分考慮",
                "value": "c"
            }
        ]
    },
    {
        "title": "運動時，你最喜歡",
        "options": [
            {
                "label": "競爭性強的運動，如籃球、足球、網球、舉重",
                "value": "d"
            },
            {
                "label": "社交性強的運動，如團體健身課、舞蹈課、羽毛球、排球",
                "value": "i"
            },
            {
                "label": "節奏穩定且持久的運動，如瑜伽、慢跑、游泳、遠足",
                "value": "s"
            },
            {
                "label": "需要精確和專注的運動，如高爾夫、射箭、攀岩、單車",
                "value": "c"
            }
        ]
    },
    {
        "title": "你採用或傾向使用的激勵技巧",
        "options": [
            {
                "label": "提供獎金、升遷或其他具有挑戰性的好處",
                "value": "d"
            },
            {
                "label": "通過讚美、公開表彰來激勵自己或他人",
                "value": "i"
            },
            {
                "label": "設立小的、可達成的目標，並在達成這些目標時給予正面的反饋",
                "value": "s"
            },
            {
                "label": "設定可衡量的績效指標和定期的績效回顧",
                "value": "c"
            }
        ]
    },
    {
        "title": "你是哪種人",
        "options": [
            {
                "label": "專注完成任務",
                "value": "d"
            },
            {
                "label": "喜歡嘗試新的活動",
                "value": "i"
            },
            {
                "label": "喜歡了解前因後果",
                "value": "c"
            },
            {
                "label": "考慮別人的感受",
                "value": "s"
            }
        ]
    },
    {
        "title": "對一個財務決定感到壓力時，最可能做出哪樣決定",
        "options": [
            {
                "label": "迅速賣掉投資或資產，即使這樣做可能會損失部分價值",
                "value": "d"
            },
            {
                "label": "向財務顧問、朋友或社交圈中的人尋求意見，並根據他們的建議來做出決策",
                "value": "i"
            },
            {
                "label": "延後做出決策，等待更多信息或市場穩定下來，再做出選擇",
                "value": "s"
            },
            {
                "label": "進行深入的市場分析，查閱各種財務報告和數據，確保所有選擇都經過充分評估後才做出決定",
                "value": "c"
            }
        ]
    },
    {
        "title": "你最喜歡藉由下列哪個方式保持放鬆",
        "options": [
            {
                "label": "健身、攀岩、極限運動",
                "value": "d"
            },
            {
                "label": "聚會、社交活動、演唱會",
                "value": "i"
            },
            {
                "label": "安排好的假期、參加有趣的課程",
                "value": "c"
            },
            {
                "label": "瑜伽、散步、閱讀",
                "value": "s"
            }
        ]
    },
    {
        "title": "你感覺最好的時候是",
        "options": [
            {
                "label": "達成目標、展現領導力和主導局面時",
                "value": "d"
            },
            {
                "label": "建立良好關係、受到讚美和認可時",
                "value": "i"
            },
            {
                "label": "處於穩定、和諧的環境中，感受到支持和協作時",
                "value": "s"
            },
            {
                "label": "能夠完成高品質的工作、達成精確的結果時",
                "value": "c"
            }
        ]
    },
    {
        "title": "當涉及到你的財務時，你更傾向因為以下感到失落",
        "options": [
            {
                "label": "高風險的財務計劃失敗",
                "value": "d"
            },
            {
                "label": "無法在社交活動中談論自己的財務成果",
                "value": "i"
            },
            {
                "label": "市場崩盤或經濟衰退",
                "value": "s"
            },
            {
                "label": "基於不完全或錯誤的資訊做出了不利的投資決策",
                "value": "c"
            }
        ]
    },
    {
        "title": "當你在社交媒體上時",
        "options": [
            {
                "label": "積極主動，利用社交媒體來展示成就和影響力",
                "value": "d"
            },
            {
                "label": "高度參與，喜歡分享和互動",
                "value": "i"
            },
            {
                "label": "較為保守，使用社交媒體來保持聯繫和分享有限信息",
                "value": "s"
            },
            {
                "label": "謹慎使用，重視隱私和準確性",
                "value": "c"
            }
        ]
    },
    {
        "title": "當說到新年新計畫時，你",
        "options": [
            {
                "label": "設立高挑戰性的目標，迅速制定計劃並付諸實行",
                "value": "d"
            },
            {
                "label": "尋求社交支持，分享計畫並獲得反饋",
                "value": "i"
            },
            {
                "label": "制定實用且可持續的計畫，逐步實施並維持穩定進展",
                "value": "s"
            },
            {
                "label": "進行詳細的研究和計劃，設立明確的步驟和檢查點",
                "value": "c"
            }
        ]
    },
    {
        "title": "涉及財務決策時，你傾向基於哪項要素做決定",
        "options": [
            {
                "label": "潛在的回報和機會",
                "value": "d"
            },
            {
                "label": "他人的意見和社會影響",
                "value": "i"
            },
            {
                "label": "穩定性和長期安全",
                "value": "s"
            },
            {
                "label": "詳細的數據和分析",
                "value": "c"
            }
        ]
    },
    {
        "title": "在餐廳選擇喝的酒時",
        "options": [
            {
                "label": "選擇高檔或有名的酒品，追求獨特或具有影響力的選擇",
                "value": "d"
            },
            {
                "label": "選擇熱門或社交性的酒品，可能會參考服務生或朋友的建議",
                "value": "i"
            },
            {
                "label": "選擇經典或熟悉的酒品，偏好穩定和可信賴的選擇",
                "value": "s"
            },
            {
                "label": "仔細研究酒單，選擇有詳細描述和評價的酒品，重視品質和準確性",
                "value": "c"
            }
        ]
    },
    {
        "title": "你有壓力或心煩意亂時，理財風格是",
        "options": [
            {
                "label": "可能會做出快速而果斷的決定，尋求短期的解決方案來應對壓力",
                "value": "d"
            },
            {
                "label": "可能會依賴他人的意見和建議，尋求社交支持來做出決策",
                "value": "i"
            },
            {
                "label": "可能會選擇保守的策略，重視穩定性和安全性",
                "value": "s"
            },
            {
                "label": "可能會進行詳細的分析和研究，尋求數據和事實來指導決策",
                "value": "c"
            }
        ]
    },
    {
        "title": "關於你的財務狀況，你不願意承認的是",
        "options": [
            {
                "label": "財務狀況的失敗或無能為力",
                "value": "d"
            },
            {
                "label": "財務問題的嚴重性或需要隱藏的困境",
                "value": "i"
            },
            {
                "label": "財務狀況的變化或不確定性",
                "value": "s"
            },
            {
                "label": "自身在財務決策中的錯誤或失誤",
                "value": "c"
            }
        ]
    },
    {
        "title": "談到消費或投資時，你最可能受到哪個群體影響",
        "options": [
            {
                "label": "成功的企業家、投資專家、行業領袖",
                "value": "d"
            },
            {
                "label": "朋友、社交圈、名人、網紅",
                "value": "i"
            },
            {
                "label": "專家、學者、財務顧問",
                "value": "c"
            },
            {
                "label": "家人、長期好友、值得信賴的顧問",
                "value": "s"
            }
        ]
    },
    {
        "title": "如果錢不是問題，你更偏好選擇哪種飛航服務",
        "options": [
            {
                "label": "直飛航班或頭等艙",
                "value": "d"
            },
            {
                "label": "額外的娛樂、餐飲或機上活動",
                "value": "i"
            },
            {
                "label": "提供更多行李配額或靈活改簽的政策",
                "value": "s"
            },
            {
                "label": "最佳性價比和詳細資訊",
                "value": "c"
            }
        ]
    }
]